mypackage/__init__.py
mypackage/fun.py
zackpkgx-0.0.2.dist-info/licenses/LICENSE.txt
zackpkgx-0.0.2.dist-info/METADATA
zackpkgx-0.0.2.dist-info/WHEEL
zackpkgx-0.0.2.dist-info/top_level.txt
zackpkgx-0.0.2.dist-info/RECORD
