Metadata-Version: 2.4
Name: zackpkgx
Version: 0.0.2
Summary: Library to print hello in my package
Author: ArabCodeX
Author-email: dina252422@gmail.com
Keywords: python,zack,hello
Classifier: Development Status :: 1 - Planning
Classifier: Intended Audience :: Developers
Classifier: Programming Language :: Python :: 3
Classifier: Operating System :: Unix
Classifier: Operating System :: MacOS :: MacOS X
Classifier: Operating System :: Microsoft :: Windows
License-File: LICENSE.txt
Dynamic: author
Dynamic: author-email
Dynamic: classifier
Dynamic: description
Dynamic: description-content-type
Dynamic: keywords
Dynamic: license-file
Dynamic: summary
